ssm_acquire/__init__.py
ssm_acquire/analyze.py
ssm_acquire/cli.py
ssm_acquire/common.py
ssm_acquire/credential.py
ssm_acquire/acquire-plans/linpmem.yml
ssm_acquire/build-plans/linpmem.yml.j2
ssm_acquire/interrogate-plans/osquery.yml.j2
ssm_acquire/polices/instance-scoped-policy.yml
ssm_acquire/transfer-plans/linpmem.yml.j2
ssm_acquire-0.1.0.4.dist-info/AUTHORS.rst
ssm_acquire-0.1.0.4.dist-info/LICENSE
ssm_acquire-0.1.0.4.dist-info/METADATA
ssm_acquire-0.1.0.4.dist-info/WHEEL
ssm_acquire-0.1.0.4.dist-info/entry_points.txt
ssm_acquire-0.1.0.4.dist-info/top_level.txt
ssm_acquire-0.1.0.4.dist-info/RECORD
