Metadata-Version: 2.1
Name: ssm-acquire
Version: 0.1.0.4
Summary: A python module for orchestrating content acquisitions and light analysis via amazon ssm.
Home-page: https://github.com/andrewkrug/ssm_acquire
Author: Andrew J Krug
Author-email: andrewkrug@gmail.com
License: MIT license
Keywords: ssm_acquire
Platform: UNKNOWN
Classifier: Development Status :: 2 - Pre-Alpha
Classifier: Intended Audience :: Developers
Classifier: License :: OSI Approved :: Mozilla Public License 2.0 (MPL 2.0)
Classifier: Natural Language :: English
Classifier: Programming Language :: Python :: 3.6
Classifier: Programming Language :: Python :: 3.7
Requires-Dist: Click (>=6.0)
Requires-Dist: pyyaml
Requires-Dist: boto3
Requires-Dist: everett
Requires-Dist: botocore
Requires-Dist: Jinja2 (>=2.10)
Requires-Dist: docker
Requires-Dist: prompt-toolkit
